llm_azure_openai.py
llm_azure_openai-0.1.6.dist-info/licenses/LICENSE
llm_azure_openai-0.1.6.dist-info/METADATA
llm_azure_openai-0.1.6.dist-info/WHEEL
llm_azure_openai-0.1.6.dist-info/entry_points.txt
llm_azure_openai-0.1.6.dist-info/top_level.txt
llm_azure_openai-0.1.6.dist-info/RECORD
