Metadata-Version: 2.4
Name: llm-azure-openai
Version: 0.1.6
Summary: LLM plugin to access Azure OpenAI models
License: Apache-2.0
Project-URL: Homepage, https://github.com/wbierbower/llm-azure-openai
Project-URL: Changelog, https://github.com/wbierbower/llm-azure-openai/releases
Project-URL: Issues, https://github.com/wbierbower/llm-azure-openai/issues
Project-URL: CI, https://github.com/wbierbower/llm-azure-openai/actions
Classifier: License :: OSI Approved :: Apache Software License
License-File: LICENSE
Requires-Dist: llm>=0.23
Requires-Dist: httpx
Requires-Dist: ijson
Requires-Dist: azure-identity>=1.10.1
Provides-Extra: test
Requires-Dist: pytest; extra == "test"
Requires-Dist: pytest-recording; extra == "test"
Requires-Dist: pytest-asyncio; extra == "test"
Requires-Dist: nest-asyncio; extra == "test"
Dynamic: license-file
